human_cursor/__init__.py
human_cursor/bezier.py
human_cursor/cursor.py
human_cursor/curve_generator.py
human_cursor/easing.py
human_cursor/models.py
human_cursor/randomizer.py
smooth_cursor_playwright-0.1.0.dist-info/METADATA
smooth_cursor_playwright-0.1.0.dist-info/WHEEL
smooth_cursor_playwright-0.1.0.dist-info/licenses/LICENSE
smooth_cursor_playwright-0.1.0.dist-info/RECORD
