Metadata-Version: 2.4
Name: smooth-cursor-playwright
Version: 0.1.0
Summary: Human-like cursor movements for Playwright automation using Bezier curves
Project-URL: Homepage, https://github.com/savonaarola/smooth-cursor-playwright
Project-URL: Repository, https://github.com/savonaarola/smooth-cursor-playwright
Project-URL: Issues, https://github.com/savonaarola/smooth-cursor-playwright/issues
License-Expression: MIT
License-File: LICENSE
Keywords: automation,bezier,bot-detection,cursor,human-like,mouse,playwright
Classifier: Development Status :: 4 - Beta
Classifier: Intended Audience :: Developers
Classifier: License :: OSI Approved :: MIT License
Classifier: Operating System :: OS Independent
Classifier: Programming Language :: Python :: 3
Classifier: Programming Language :: Python :: 3.10
Classifier: Programming Language :: Python :: 3.11
Classifier: Programming Language :: Python :: 3.12
Classifier: Programming Language :: Python :: 3.13
Classifier: Topic :: Software Development :: Libraries :: Python Modules
Classifier: Topic :: Software Development :: Testing
Requires-Python: >=3.10
Requires-Dist: playwright>=1.40.0
